PrusaLinkPy/__init__.py
tests/__init__.py
tests/test_PrusaLinkPy.py
PrusaLinkPy-2.2.1.dist-info/LICENSE
PrusaLinkPy-2.2.1.dist-info/METADATA
PrusaLinkPy-2.2.1.dist-info/WHEEL
PrusaLinkPy-2.2.1.dist-info/top_level.txt
PrusaLinkPy-2.2.1.dist-info/RECORD
