Metadata-Version: 2.1
Name: PrusaLinkPy
Version: 2.2.1
Summary: A library to interface with the PrusaLink API
Author: Guillaume RICO
Author-email: Guillaume RICO <guillaume.rico@alpesmesures.fr>
License: Copyright (c) 2023 Guillaume RICO
Project-URL: Homepage, https://github.com/guillaume-rico/PrusaLinkPy
Project-URL: Bug Tracker, https://github.com/guillaume-rico/PrusaLinkPy/issues
Project-URL: repository, https://github.com/guillaume-rico/PrusaLinkPy.git
Keywords: Prusalink,API,Mini
Classifier: Programming Language :: Python :: 3
Classifier: License :: OSI Approved :: MIT License
Classifier: Operating System :: OS Independent
Requires-Python: >=3.7
License-File: LICENSE
